shooterdriver/__init__.py
shooterdriver-1.0.3.dist-info/METADATA
shooterdriver-1.0.3.dist-info/WHEEL
shooterdriver-1.0.3.dist-info/licenses/LICENSE
shooterdriver-1.0.3.dist-info/RECORD
