Metadata-Version: 2.1
Name: shooterdriver
Version: 1.0.3
Summary: A library for controlling the T2M Shooter RC Car through Python.
Project-URL: Homepage, https://github.com/Thomas-More-Digital-Innovation/2223-DI-005-Race-To-The-Future
Project-URL: Bug Tracker, https://github.com/Thomas-More-Digital-Innovation/2223-DI-005-Race-To-The-Future/issues
Author-email: Jonas Claes <jonas@jonasclaes.be>
License: MIT License
License-File: LICENSE
Classifier: License :: OSI Approved :: MIT License
Classifier: Operating System :: OS Independent
Classifier: Programming Language :: Python :: 3
Requires-Python: >=3.9
